flake8_django/__init__.py
flake8_django/checker.py
flake8_django/checkers/__init__.py
flake8_django/checkers/base_model_checker.py
flake8_django/checkers/checker.py
flake8_django/checkers/decorator.py
flake8_django/checkers/issue.py
flake8_django/checkers/model_content_order.py
flake8_django/checkers/model_dunder_str.py
flake8_django/checkers/model_fields.py
flake8_django/checkers/model_form.py
flake8_django/checkers/model_meta.py
flake8_django/checkers/render.py
flake8_django/checkers/utils.py
flake8_django_hhupd-1.4.1.dist-info/LICENSE
flake8_django_hhupd-1.4.1.dist-info/METADATA
flake8_django_hhupd-1.4.1.dist-info/WHEEL
flake8_django_hhupd-1.4.1.dist-info/entry_points.txt
flake8_django_hhupd-1.4.1.dist-info/RECORD
