Metadata-Version: 2.1
Name: flake8-django-hhupd
Version: 1.4.1
Summary: Plugin to catch bad style specific to Django Projects.
Home-page: https://github.com/rocioar/flake8-django
License: GPL-3.0-or-later
Keywords: flake8,django,lint
Author: Rocio Aramberri Schegel
Author-email: rocio.aramberri@schegel.net
Requires-Python: >=3.8,<4.0
Classifier: Framework :: Flake8
Classifier: License :: OSI Approved :: GNU General Public License v3 or later (GPLv3+)
Classifier: Programming Language :: Python :: 3
Classifier: Programming Language :: Python :: 3.8
Classifier: Programming Language :: Python :: 3.9
Classifier: Programming Language :: Python :: 3.10
Classifier: Programming Language :: Python :: 3.11
Classifier: Programming Language :: Python :: 3.12
Classifier: Topic :: Software Development :: Libraries :: Python Modules
Classifier: Topic :: Software Development :: Quality Assurance
Requires-Dist: astroid (>=3.0.1,<4.0.0)
Requires-Dist: flake8 (>=3.8.4,<8)
Project-URL: Repository, https://github.com/rocioar/flake8-django
